Boboboncio/Prueba1.py
Boboboncio/__init__.py
boboboncio-0.1.dist-info/METADATA
boboboncio-0.1.dist-info/WHEEL
boboboncio-0.1.dist-info/top_level.txt
boboboncio-0.1.dist-info/RECORD
