Metadata-Version: 2.2
Name: Boboboncio
Version: 0.1
Summary: Copyright lololol
Home-page: https://github.com/Boncio4/LibreriaPrueba.git
Author: Boncete
Author-email: 179552318+Boncio4@users.noreply.github.com
Classifier: Programming Language :: Python :: 3
Dynamic: author
Dynamic: author-email
Dynamic: classifier
Dynamic: home-page
Dynamic: summary
